[{"line":2,"elements":[{"line":5,"name":"","description":"","type":"background","keyword":"Background","steps":[{"result":{"duration":9582256300,"status":"passed"},"line":6,"name":"user is on login page","match":{"location":"Assignment.AssignmentOrangeCode.user_is_on_login_page()"},"keyword":"Given "},{"result":{"duration":247892100,"status":"passed"},"line":7,"name":"user enters username and password","match":{"location":"Assignment.AssignmentOrangeCode.user_is_on_()"},"keyword":"When "},{"result":{"duration":5017366700,"status":"passed"},"line":8,"name":"clicks on login page","match":{"location":"Assignment.AssignmentOrangeCode.user_is_on()"},"keyword":"When "}]},{"start_timestamp":"2022-07-19T03:40:55.332Z","line":11,"name":"1 check User Role Column","description":"","id":"test-orange-hrm-website;1-check-user-role-column","type":"scenario","keyword":"Scenario","steps":[{"result":{"duration":1704939800,"status":"passed"},"line":13,"name":"user clicks on Go To Admin","match":{"location":"Assignment.AssignmentOrangeCode.user_is_o()"},"keyword":"When "},{"result":{"duration":116703400,"status":"passed"},"line":14,"name":"user clicks on user management","match":{"location":"Assignment.AssignmentOrangeCode.user_is_()"},"keyword":"And "},{"result":{"duration":1076185900,"status":"passed"},"line":15,"name":"user clicks on Users","match":{"location":"Assignment.AssignmentOrangeCode.user_is()"},"keyword":"And "},{"result":{"duration":115232400,"status":"passed"},"line":16,"name":"Verify User Role Column","match":{"location":"Assignment.AssignmentOrangeCode.user_i()"},"keyword":"Then "},{"result":{"duration":1850291600,"status":"passed"},"line":17,"name":"Logout and Close Browsers","match":{"location":"Assignment.AssignmentOrangeCode.us1()"},"keyword":"Then "}]},{"line":5,"name":"","description":"","type":"background","keyword":"Background","steps":[{"result":{"duration":6166669000,"status":"passed"},"line":6,"name":"user is on login page","match":{"location":"Assignment.AssignmentOrangeCode.user_is_on_login_page()"},"keyword":"Given "},{"result":{"duration":234491200,"status":"passed"},"line":7,"name":"user enters username and password","match":{"location":"Assignment.AssignmentOrangeCode.user_is_on_()"},"keyword":"When "},{"result":{"duration":4598169000,"status":"passed"},"line":8,"name":"clicks on login page","match":{"location":"Assignment.AssignmentOrangeCode.user_is_on()"},"keyword":"When "}]},{"start_timestamp":"2022-07-19T03:41:15.132Z","line":19,"name":"2 check Employee Name Column","description":"","id":"test-orange-hrm-website;2-check-employee-name-column","type":"scenario","keyword":"Scenario","steps":[{"result":{"duration":2128461600,"status":"passed"},"line":21,"name":"user clicks on Go To Leave","match":{"location":"Assignment.AssignmentOrangeCode.user()"},"keyword":"When "},{"result":{"duration":784527400,"status":"passed"},"line":22,"name":"user clicks on My Leave","match":{"location":"Assignment.AssignmentOrangeCode.use()"},"keyword":"And "},{"result":{"duration":1885432100,"status":"passed"},"line":23,"name":"Verify Employee Name Column","match":{"location":"Assignment.AssignmentOrangeCode.ue()"},"keyword":"Then "},{"result":{"duration":1625078900,"status":"passed"},"line":24,"name":"Logout and Close Browser","match":{"location":"Assignment.AssignmentOrangeCode.us()"},"keyword":"Then "}]}],"name":"Test Orange HRM website","description":"","id":"test-orange-hrm-website","keyword":"Feature","uri":"file:src/test/resources/Features/orangeHRM.feature","tags":[]}]